python_settings/__init__.py
python_settings/exceptions.py
python_settings/tests/__init__.py
python_settings/tests/test_python_settings.py
python_settings/tests/settings/__init__.py
python_settings/tests/settings/base_settings.py
python_settings/tests/settings/development_settings.py
python_settings/tests/settings/lazy_settings.py
python_settings-0.2.2.dist-info/LICENSE.txt
python_settings-0.2.2.dist-info/METADATA
python_settings-0.2.2.dist-info/WHEEL
python_settings-0.2.2.dist-info/top_level.txt
python_settings-0.2.2.dist-info/RECORD
