Metadata-Version: 2.1
Name: python-settings
Version: 0.2.2
Summary: This module provides you easy access to your config/settings properties from all your python modules
Home-page: https://github.com/charlsagente/python-settings
Author: Carlos Perez
Author-email: charlsagente@gmail.com
License: MIT
Platform: UNKNOWN
Classifier: Intended Audience :: Developers
Classifier: Operating System :: OS Independent
Classifier: Topic :: Utilities
Classifier: Programming Language :: Python
